stochastics/__init__.py
stochastics/config.py
stochastics/errors.py
stochastics/utils.py
stochastics/models/__init__.py
stochastics/models/custom_types.py
stochastics/models/markov_chain.py
stochastics-0.4.0.dist-info/LICENSE
stochastics-0.4.0.dist-info/METADATA
stochastics-0.4.0.dist-info/WHEEL
stochastics-0.4.0.dist-info/top_level.txt
stochastics-0.4.0.dist-info/RECORD
