Metadata-Version: 2.1
Name: stochastics
Version: 0.4.0
Summary: Python solution for Stochastics
Home-page: https://github.com/deadpyxel/stochastics
Author: deadpyxel
Author-email: ghost0092@gmail.com
License: MIT
Platform: UNKNOWN
Classifier: License :: OSI Approved :: MIT License
Classifier: Programming Language :: Python :: 3
Classifier: Programming Language :: Python :: 3 :: Only
Classifier: Programming Language :: Python :: 3.8
Classifier: Programming Language :: Python :: 3.9
Classifier: Programming Language :: Python :: Implementation :: CPython
Requires-Python: >=3.8
